phylogenie/__init__.py
phylogenie/draw.py
phylogenie/main.py
phylogenie/mixins.py
phylogenie/msa.py
phylogenie/py.typed
phylogenie/typeguards.py
phylogenie/typings.py
phylogenie/generators/__init__.py
phylogenie/generators/alisim.py
phylogenie/generators/configs.py
phylogenie/generators/dataset.py
phylogenie/generators/factories.py
phylogenie/generators/trees.py
phylogenie/generators/typeguards.py
phylogenie/io/__init__.py
phylogenie/io/fasta.py
phylogenie/skyline/__init__.py
phylogenie/skyline/matrix.py
phylogenie/skyline/parameter.py
phylogenie/skyline/vector.py
phylogenie/treesimulator/__init__.py
phylogenie/treesimulator/features.py
phylogenie/treesimulator/gillespie.py
phylogenie/treesimulator/model.py
phylogenie/treesimulator/tree.py
phylogenie/treesimulator/utils.py
phylogenie/treesimulator/events/__init__.py
phylogenie/treesimulator/events/base.py
phylogenie/treesimulator/events/contact_tracing.py
phylogenie/treesimulator/events/core.py
phylogenie/treesimulator/events/mutations.py
phylogenie/treesimulator/io/__init__.py
phylogenie/treesimulator/io/newick.py
phylogenie/treesimulator/io/nexus.py
phylogenie-3.1.17.dist-info/licenses/LICENSE.txt
phylogenie-3.1.17.dist-info/METADATA
phylogenie-3.1.17.dist-info/WHEEL
phylogenie-3.1.17.dist-info/entry_points.txt
phylogenie-3.1.17.dist-info/top_level.txt
phylogenie-3.1.17.dist-info/RECORD
