Metadata-Version: 2.4
Name: phylogenie
Version: 3.1.17
Summary: Generate phylogenetic datasets with minimal setup effort
Requires-Python: >=3.10
License-File: LICENSE.txt
Requires-Dist: joblib>=1.5.2
Requires-Dist: matplotlib>=3.10.7
Requires-Dist: pandas>=2.3.3
Requires-Dist: pydantic>=2.12.3
Requires-Dist: pyyaml>=6.0.3
Requires-Dist: tqdm>=4.67.1
Dynamic: license-file
